.tox/release/lib/python3.13/site-packages/smithy_dafny_standard_library/internaldafny/generated/Actions.py
.tox/release/lib/python3.13/site-packages/smithy_dafny_standard_library/internaldafny/generated/Base64.py
.tox/release/lib/python3.13/site-packages/smithy_dafny_standard_library/internaldafny/generated/Base64Lemmas.py
.tox/release/lib/python3.13/site-packages/smithy_dafny_standard_library/internaldafny/generated/BoundedInts.py
.tox/release/lib/python3.13/site-packages/smithy_dafny_standard_library/internaldafny/generated/ConcurrentCall.py
.tox/release/lib/python3.13/site-packages/smithy_dafny_standard_library/internaldafny/generated/DafnyLibraries.py
.tox/release/lib/python3.13/site-packages/smithy_dafny_standard_library/internaldafny/generated/DivInternals.py
.tox/release/lib/python3.13/site-packages/smithy_dafny_standard_library/internaldafny/generated/DivInternalsNonlinear.py
.tox/release/lib/python3.13/site-packages/smithy_dafny_standard_library/internaldafny/generated/DivMod.py
.tox/release/lib/python3.13/site-packages/smithy_dafny_standard_library/internaldafny/generated/FileIO.py
.tox/release/lib/python3.13/site-packages/smithy_dafny_standard_library/internaldafny/generated/FloatCompare.py
.tox/release/lib/python3.13/site-packages/smithy_dafny_standard_library/internaldafny/generated/Functions.py
.tox/release/lib/python3.13/site-packages/smithy_dafny_standard_library/internaldafny/generated/GeneralInternals.py
.tox/release/lib/python3.13/site-packages/smithy_dafny_standard_library/internaldafny/generated/GetOpt.py
.tox/release/lib/python3.13/site-packages/smithy_dafny_standard_library/internaldafny/generated/HexStrings.py
.tox/release/lib/python3.13/site-packages/smithy_dafny_standard_library/internaldafny/generated/JSON.py
.tox/release/lib/python3.13/site-packages/smithy_dafny_standard_library/internaldafny/generated/JSON_API.py
.tox/release/lib/python3.13/site-packages/smithy_dafny_standard_library/internaldafny/generated/JSON_ConcreteSyntax.py
aws_cryptography_internal_primitives-1.11.1.dist-info/METADATA
aws_cryptography_internal_primitives-1.11.1.dist-info/WHEEL
aws_cryptography_internal_primitives-1.11.1.dist-info/RECORD
